kdb_vault_tools/__init__.py
kdb_vault_tools/exceptions.py
kdb_vault_tools/processors.py
kdb_vault_tools/datatypes/__init__.py
kdb_vault_tools/datatypes/basic.py
tests/__init__.py
tests/test_basics.py
tests/test_kdb_processor.py
tests/test_kdb_vault_processor.py
tests/test_vault_processor.py
tests/utils.py
kdb_vault_tools-0.1.6.dist-info/LICENSE.txt
kdb_vault_tools-0.1.6.dist-info/METADATA
kdb_vault_tools-0.1.6.dist-info/WHEEL
kdb_vault_tools-0.1.6.dist-info/top_level.txt
kdb_vault_tools-0.1.6.dist-info/RECORD
