Metadata-Version: 2.1
Name: kdb-vault-tools
Version: 0.1.6
Summary: Tools for kdb vault managing
Home-page: https://github.com/moaddib666/kdb-vault-tools
Author: Max Nikitenko
Author-email: moaddib666@gmail.com
License: MIT
Platform: UNKNOWN
Classifier: Programming Language :: Python :: 3
Classifier: License :: OSI Approved :: MIT License
Classifier: Operating System :: OS Independent
Requires-Dist: pykeepass (==4.0.0)
Requires-Dist: hvac (==0.10.8)
